{
  "name": "Airdramon",
  "stage": "Champion",
  "attribute": "Vaccine",
  "element": "Water",
  "archetype": "Mystic",
  "size": "Large",
  "stats": {
    "CRG": 4,
    "FRD": 4,
    "LVE": 7,
    "KNW": 8,
    "SNC": 5,
    "RLB": 4
  },
  "signature_move": {
    "name": "Spinning Needle",
    "element": "Wind",
    "pr": 5,
    "tags": "[RANGE 4]",
    "description": "Shoots needle-shaped vacuum blades from its wings."
  },
  "digivolves_from": [
    "Agumon",
    "Agumon (Black)",
    "Betamon",
    "Candmon",
    "DORUmon",
    "Flamon",
    "Goburimon",
    "Gottsumon",
    "Guilmon",
    "Hawkmon",
    "Impmon",
    "Kunemon",
    "Monodramon",
    "Muchomon",
    "Patamon",
    "Penmon",
    "Piyomon",
    "Plotmon",
    "Ryudamon",
    "Tentomon",
    "Tukaimon",
    "V-mon",
    "Wormmon",
    "Yuki Agumon"
  ],
  "digivolves_to": [
    "Aero V-dramon",
    "Andiramon",
    "Cyberdramon",
    "Delumon",
    "Garudamon",
    "Gigadramon",
    "Giromon",
    "Hisyaryumon",
    "Indaramon",
    "Karatenmon",
    "Kumbhiramon",
    "Mamemon",
    "Mametyramon",
    "Megadramon",
    "Megalo Growmon",
    "Metal Greymon",
    "Metal Greymon (Virus)",
    "Metal Tyranomon",
    "Monzaemon",
    "Parrotmon",
    "Phelesmon",
    "Piccolomon",
    "Rize Greymon",
    "Sandiramon",
    "Silphymon",
    "Sinduramon",
    "Vademon",
    "Vamdemon",
    "Wingdramon",
    "Mega Seadramon",
    "Hippogriffomon"
  ],
  "needs_review": false,
  "review_notes": "automation",
  "description": "A Mythical Beast Digimon that grew gigantic wings. It's a highly valued monster due to it being said to have an existence close to that of a god. It specializes in mid-air attacks, its roar calls forth storms, and it causes giant tornadoes by flapping its wings. Its personality is considerably brutal, but it has great intelligence. However, being employed by an ordinary Tamer doesn't seem possible. Its Special Move is flapping its enormous wings to send out a sharp vacuum blade, ( Spinning Needle ).",
  "web_created": true
}