{
  "name": "Piccolomon",
  "stage": "Ultimate",
  "attribute": "Vaccine",
  "element": "Neutral",
  "archetype": "Support",
  "size": "Large",
  "stats": {
    "CRG": 9,
    "FRD": 7,
    "LVE": 10,
    "KNW": 9,
    "SNC": 8,
    "RLB": 7
  },
  "signature_move": {
    "name": "Bit Bomb",
    "element": "Neutral",
    "pr": 10,
    "tags": "[RANGE 2]",
    "description": "Conjures up a flying bomb shaped like a bat made from a computer virus."
  },
  "digivolves_from": [
    "Airdramon",
    "Akatorimon",
    "Angemon",
    "Ankylomon",
    "Black Tailmon Uver.",
    "Boarmon",
    "Cockatrimon",
    "DORUgamon",
    "Darcmon",
    "Devidramon",
    "Dokugumon",
    "Hover Espimon",
    "Igamon",
    "Kiwimon",
    "Kuwagamon",
    "Leomon",
    "Mojyamon",
    "Peckmon",
    "Pegasmon",
    "Reppamon",
    "Shellmon",
    "Shima Unimon",
    "Sorcerimon",
    "Thunderballmon",
    "Togemon",
    "Unimon",
    "Vegimon",
    "Wizarmon",
    "Woodmon"
  ],
  "digivolves_to": [
    "Babamon",
    "Bacchusmon",
    "Bloom Lordmon",
    "Bryweludramon",
    "Cherubimon (Virtue)",
    "Clavis Angemon",
    "Devitamamon",
    "El Doradimon",
    "Griffomon",
    "Hououmon",
    "Jijimon",
    "Marin Angemon",
    "Marsmon",
    "Ofanimon",
    "Piemon",
    "Rosemon",
    "Sleipmon",
    "Venusmon",
    "Victory Greymon",
    "War Greymon",
    "Z'd Garurumon"
  ],
  "needs_review": false,
  "review_notes": "",
  "web_created": true,
  "description": "A Fairy Digimon that is fluent in magic. It can recite the advanced programming language of another dimension, allowing it to generate miracles with the appearance of magic. This miraculous Digimon is able to pop up in every place, time, and space, and although its body is small, it can seal away the enemy's abilities with its own special ability, and then pulverize the opponent with a mighty blow. With its mischief-loving personality, it enjoys making computers run wild with its cherished spear, \" Fairy Tale \", that it always holds in its hands (although it has no ill intent). Its Special Move is a super-powerful bomb packed with computer viruses ( Bit Bomb ). Despite its appearance, it uses terrifying attacks."
}