{
  "name": "Shamamon",
  "stage": "Rookie",
  "attribute": "Virus",
  "element": "Neutral",
  "archetype": "Balanced",
  "size": "Medium",
  "stats": {
    "CRG": 5,
    "FRD": 4,
    "LVE": 4,
    "KNW": 5,
    "SNC": 2,
    "RLB": 2
  },
  "signature_move": {
    "name": "Shama Hammer",
    "element": "Neutral",
    "pr": 4,
    "tags": "[MELEE]",
    "description": "Strikes the enemy's head with the large club it uses for its rituals."
  },
  "digivolves_from": [
    "Chocomon",
    "Dorimon",
    "Tsumemon",
    "Tunomon"
  ],
  "digivolves_to": [
    "Bakemon",
    "Black Galgomon",
    "Cyclomon",
    "Dark Lizamon",
    "Fugamon",
    "Gargomon",
    "Garurumon",
    "Geremon",
    "Gorimon",
    "Growmon",
    "Hanumon",
    "Harpymon",
    "Icemon",
    "Igamon",
    "Kabukimon",
    "Kougamon",
    "Kuwagamon",
    "Kyubimon",
    "Meramon",
    "Minotaurmon",
    "Musyamon",
    "Numemon",
    "Orgemon",
    "Porcupamon",
    "Prairiemon",
    "Scumon",
    "Sepikmon",
    "Sorcerimon",
    "Soulmon",
    "Stingmon",
    "Vegimon",
    "Witchmon",
    "Youkomon",
    "Ogremon"
  ],
  "needs_review": true,
  "review_notes": "automation",
  "web_created": true,
  "description": "A Goburimon whose duty is to listen to the will of God , and convey that to its clan. It performs a mysterious dance during its rituals, and it is said that once it gets fired up to the maximum, it becomes able to hear the prophecies of God. It also makes use of this ritual to predict matters that are of importance to its clan. Its Special Move is striking the enemy's head with the large club it uses for its rituals ( Shama Hammer )."
}